oxford_stats_lib/__init__.py
oxford_stats_lib-1.1.7.dist-info/licenses/LICENSE
oxford_stats_lib-1.1.7.dist-info/METADATA
oxford_stats_lib-1.1.7.dist-info/WHEEL
oxford_stats_lib-1.1.7.dist-info/top_level.txt
oxford_stats_lib-1.1.7.dist-info/RECORD
