Metadata-Version: 2.4
Name: oxford_stats_lib
Version: 1.1.7
Summary: A library for wrangling data for University of Oxford Intro to Probability Theory and Statistics
Author-email: Geza Kerecsenyi <geza@kerecs.com>
Classifier: Programming Language :: Python :: 3
Classifier: License :: OSI Approved :: MIT License
Classifier: Operating System :: OS Independent
Requires-Python: >=3.9
License-File: LICENSE
Dynamic: license-file
